ji/__init__.py
ji-0.0.7.dist-info/licenses/LICENSE
ji-0.0.7.dist-info/METADATA
ji-0.0.7.dist-info/WHEEL
ji-0.0.7.dist-info/top_level.txt
ji-0.0.7.dist-info/RECORD
