Metadata-Version: 2.4
Name: ji
Version: 0.0.7
Summary: An illustration of various embeddings
Home-page: https://github.com/t-c-w/ji
License: apache-2.0
Platform: any
License-File: LICENSE
Requires-Dist: scikit-learn
Dynamic: license-file
